{
  "__inputs": [
    {
      "name": "DS_PROMETHEUS",
      "label": "Prometheus",
      "description": "Prometheus data source for ShieldOps metrics",
      "type": "datasource",
      "pluginId": "prometheus",
      "pluginName": "Prometheus"
    }
  ],
  "__requires": [
    {
      "type": "grafana",
      "id": "grafana",
      "name": "Grafana",
      "version": "10.0.0"
    },
    {
      "type": "datasource",
      "id": "prometheus",
      "name": "Prometheus",
      "version": "1.0.0"
    },
    {
      "type": "panel",
      "id": "timeseries",
      "name": "Time series",
      "version": ""
    },
    {
      "type": "panel",
      "id": "gauge",
      "name": "Gauge",
      "version": ""
    },
    {
      "type": "panel",
      "id": "barchart",
      "name": "Bar chart",
      "version": ""
    },
    {
      "type": "panel",
      "id": "stat",
      "name": "Stat",
      "version": ""
    }
  ],
  "annotations": {
    "list": [
      {
        "builtIn": 1,
        "datasource": {
          "type": "grafana",
          "uid": "-- Grafana --"
        },
        "enable": true,
        "hide": true,
        "iconColor": "rgba(0, 211, 255, 1)",
        "name": "Annotations & Alerts",
        "type": "dashboard"
      }
    ]
  },
  "description": "ShieldOps platform overview: HTTP traffic, latency, endpoint performance, and agent health",
  "editable": true,
  "fiscalYearStartMonth": 0,
  "graphTooltip": 1,
  "id": null,
  "links": [],
  "panels": [
    {
      "collapsed": false,
      "gridPos": { "h": 1, "w": 24, "x": 0, "y": 0 },
      "id": 100,
      "title": "HTTP Overview",
      "type": "row"
    },
    {
      "datasource": { "type": "prometheus", "uid": "${DS_PROMETHEUS}" },
      "description": "HTTP request rate per second, broken down by status code",
      "fieldConfig": {
        "defaults": {
          "color": { "mode": "palette-classic" },
          "custom": {
            "axisBorderShow": false,
            "axisCenteredZero": false,
            "axisLabel": "req/s",
            "axisPlacement": "auto",
            "barAlignment": 0,
            "drawStyle": "line",
            "fillOpacity": 15,
            "gradientMode": "none",
            "hideFrom": { "legend": false, "tooltip": false, "viz": false },
            "insertNulls": false,
            "lineInterpolation": "smooth",
            "lineWidth": 2,
            "pointSize": 5,
            "scaleDistribution": { "type": "linear" },
            "showPoints": "never",
            "spanNulls": false,
            "stacking": { "group": "A", "mode": "none" },
            "thresholdsStyle": { "mode": "off" }
          },
          "mappings": [],
          "thresholds": {
            "mode": "absolute",
            "steps": [
              { "color": "green", "value": null },
              { "color": "red", "value": 80 }
            ]
          },
          "unit": "reqps"
        },
        "overrides": [
          {
            "matcher": { "id": "byRegexp", "options": ".*5[0-9]{2}.*" },
            "properties": [
              { "id": "color", "value": { "fixedColor": "red", "mode": "fixed" } }
            ]
          },
          {
            "matcher": { "id": "byRegexp", "options": ".*4[0-9]{2}.*" },
            "properties": [
              { "id": "color", "value": { "fixedColor": "orange", "mode": "fixed" } }
            ]
          },
          {
            "matcher": { "id": "byRegexp", "options": ".*2[0-9]{2}.*" },
            "properties": [
              { "id": "color", "value": { "fixedColor": "green", "mode": "fixed" } }
            ]
          }
        ]
      },
      "gridPos": { "h": 8, "w": 6, "x": 0, "y": 1 },
      "id": 1,
      "options": {
        "legend": { "calcs": ["mean", "max"], "displayMode": "table", "placement": "bottom" },
        "tooltip": { "mode": "multi", "sort": "desc" }
      },
      "targets": [
        {
          "datasource": { "type": "prometheus", "uid": "${DS_PROMETHEUS}" },
          "editorMode": "code",
          "expr": "sum by (status_code) (rate(http_requests_total[5m]))",
          "legendFormat": "{{status_code}}",
          "range": true,
          "refId": "A"
        }
      ],
      "title": "Request Rate",
      "type": "timeseries"
    },
    {
      "datasource": { "type": "prometheus", "uid": "${DS_PROMETHEUS}" },
      "description": "Rate of HTTP 5xx server errors per second",
      "fieldConfig": {
        "defaults": {
          "color": { "fixedColor": "red", "mode": "fixed" },
          "custom": {
            "axisBorderShow": false,
            "axisCenteredZero": false,
            "axisLabel": "errors/s",
            "axisPlacement": "auto",
            "barAlignment": 0,
            "drawStyle": "line",
            "fillOpacity": 25,
            "gradientMode": "scheme",
            "hideFrom": { "legend": false, "tooltip": false, "viz": false },
            "insertNulls": false,
            "lineInterpolation": "smooth",
            "lineWidth": 2,
            "pointSize": 5,
            "scaleDistribution": { "type": "linear" },
            "showPoints": "never",
            "spanNulls": false,
            "stacking": { "group": "A", "mode": "none" },
            "thresholdsStyle": { "mode": "area" }
          },
          "mappings": [],
          "thresholds": {
            "mode": "absolute",
            "steps": [
              { "color": "transparent", "value": null },
              { "color": "red", "value": 0.5 }
            ]
          },
          "unit": "reqps"
        },
        "overrides": []
      },
      "gridPos": { "h": 8, "w": 6, "x": 6, "y": 1 },
      "id": 2,
      "options": {
        "legend": { "calcs": ["mean", "max"], "displayMode": "table", "placement": "bottom" },
        "tooltip": { "mode": "multi", "sort": "desc" }
      },
      "targets": [
        {
          "datasource": { "type": "prometheus", "uid": "${DS_PROMETHEUS}" },
          "editorMode": "code",
          "expr": "sum(rate(http_requests_total{status_code=~\"5..\"}[5m]))",
          "legendFormat": "5xx errors",
          "range": true,
          "refId": "A"
        },
        {
          "datasource": { "type": "prometheus", "uid": "${DS_PROMETHEUS}" },
          "editorMode": "code",
          "expr": "sum(rate(http_requests_total{status_code=~\"5..\"}[5m])) / sum(rate(http_requests_total[5m])) * 100",
          "legendFormat": "Error % (right axis)",
          "range": true,
          "refId": "B",
          "hide": false
        }
      ],
      "title": "Error Rate (5xx)",
      "type": "timeseries"
    },
    {
      "datasource": { "type": "prometheus", "uid": "${DS_PROMETHEUS}" },
      "description": "HTTP request latency at P50, P95, and P99 percentiles",
      "fieldConfig": {
        "defaults": {
          "color": { "mode": "palette-classic" },
          "custom": {
            "axisBorderShow": false,
            "axisCenteredZero": false,
            "axisLabel": "latency",
            "axisPlacement": "auto",
            "barAlignment": 0,
            "drawStyle": "line",
            "fillOpacity": 10,
            "gradientMode": "none",
            "hideFrom": { "legend": false, "tooltip": false, "viz": false },
            "insertNulls": false,
            "lineInterpolation": "smooth",
            "lineWidth": 2,
            "pointSize": 5,
            "scaleDistribution": { "type": "linear" },
            "showPoints": "never",
            "spanNulls": false,
            "stacking": { "group": "A", "mode": "none" },
            "thresholdsStyle": { "mode": "line+area" }
          },
          "mappings": [],
          "thresholds": {
            "mode": "absolute",
            "steps": [
              { "color": "transparent", "value": null },
              { "color": "orange", "value": 2 },
              { "color": "red", "value": 5 }
            ]
          },
          "unit": "s"
        },
        "overrides": [
          {
            "matcher": { "id": "byName", "options": "P99" },
            "properties": [
              { "id": "color", "value": { "fixedColor": "red", "mode": "fixed" } }
            ]
          },
          {
            "matcher": { "id": "byName", "options": "P95" },
            "properties": [
              { "id": "color", "value": { "fixedColor": "orange", "mode": "fixed" } }
            ]
          },
          {
            "matcher": { "id": "byName", "options": "P50" },
            "properties": [
              { "id": "color", "value": { "fixedColor": "green", "mode": "fixed" } }
            ]
          }
        ]
      },
      "gridPos": { "h": 8, "w": 6, "x": 12, "y": 1 },
      "id": 3,
      "options": {
        "legend": { "calcs": ["mean", "max"], "displayMode": "table", "placement": "bottom" },
        "tooltip": { "mode": "multi", "sort": "desc" }
      },
      "targets": [
        {
          "datasource": { "type": "prometheus", "uid": "${DS_PROMETHEUS}" },
          "editorMode": "code",
          "expr": "histogram_quantile(0.50, sum by (le) (rate(http_request_duration_seconds_bucket[5m])))",
          "legendFormat": "P50",
          "range": true,
          "refId": "A"
        },
        {
          "datasource": { "type": "prometheus", "uid": "${DS_PROMETHEUS}" },
          "editorMode": "code",
          "expr": "histogram_quantile(0.95, sum by (le) (rate(http_request_duration_seconds_bucket[5m])))",
          "legendFormat": "P95",
          "range": true,
          "refId": "B"
        },
        {
          "datasource": { "type": "prometheus", "uid": "${DS_PROMETHEUS}" },
          "editorMode": "code",
          "expr": "histogram_quantile(0.99, sum by (le) (rate(http_request_duration_seconds_bucket[5m])))",
          "legendFormat": "P99",
          "range": true,
          "refId": "C"
        }
      ],
      "title": "P50 / P95 / P99 Latency",
      "type": "timeseries"
    },
    {
      "datasource": { "type": "prometheus", "uid": "${DS_PROMETHEUS}" },
      "description": "Number of HTTP requests currently being processed",
      "fieldConfig": {
        "defaults": {
          "color": { "mode": "thresholds" },
          "mappings": [],
          "thresholds": {
            "mode": "absolute",
            "steps": [
              { "color": "green", "value": null },
              { "color": "yellow", "value": 50 },
              { "color": "orange", "value": 100 },
              { "color": "red", "value": 200 }
            ]
          },
          "unit": "none"
        },
        "overrides": []
      },
      "gridPos": { "h": 8, "w": 6, "x": 18, "y": 1 },
      "id": 4,
      "options": {
        "minVizHeight": 75,
        "minVizWidth": 75,
        "orientation": "auto",
        "reduceOptions": {
          "calcs": ["lastNotNull"],
          "fields": "",
          "values": false
        },
        "showThresholdLabels": false,
        "showThresholdMarkers": true,
        "sizing": "auto"
      },
      "targets": [
        {
          "datasource": { "type": "prometheus", "uid": "${DS_PROMETHEUS}" },
          "editorMode": "code",
          "expr": "sum(http_requests_in_progress)",
          "legendFormat": "In-Flight",
          "instant": true,
          "refId": "A"
        }
      ],
      "title": "In-Flight Requests",
      "type": "gauge"
    },
    {
      "collapsed": false,
      "gridPos": { "h": 1, "w": 24, "x": 0, "y": 9 },
      "id": 200,
      "title": "Endpoint Performance",
      "type": "row"
    },
    {
      "datasource": { "type": "prometheus", "uid": "${DS_PROMETHEUS}" },
      "description": "Top 10 endpoints ranked by total request count over the selected time range",
      "fieldConfig": {
        "defaults": {
          "color": { "mode": "palette-classic" },
          "custom": {
            "axisBorderShow": false,
            "axisCenteredZero": false,
            "axisLabel": "requests",
            "axisPlacement": "auto",
            "fillOpacity": 80,
            "gradientMode": "none",
            "hideFrom": { "legend": false, "tooltip": false, "viz": false },
            "lineWidth": 1,
            "scaleDistribution": { "type": "linear" }
          },
          "mappings": [],
          "thresholds": {
            "mode": "absolute",
            "steps": [
              { "color": "green", "value": null }
            ]
          },
          "unit": "short"
        },
        "overrides": []
      },
      "gridPos": { "h": 8, "w": 12, "x": 0, "y": 10 },
      "id": 5,
      "options": {
        "barRadius": 0.1,
        "barWidth": 0.7,
        "fullHighlight": false,
        "groupWidth": 0.7,
        "legend": { "displayMode": "list", "placement": "bottom" },
        "orientation": "horizontal",
        "showValue": "auto",
        "stacking": "none",
        "tooltip": { "mode": "single", "sort": "none" },
        "xTickLabelRotation": 0
      },
      "targets": [
        {
          "datasource": { "type": "prometheus", "uid": "${DS_PROMETHEUS}" },
          "editorMode": "code",
          "expr": "topk(10, sum by (path_template) (increase(http_requests_total[1h])))",
          "legendFormat": "{{path_template}}",
          "instant": true,
          "refId": "A"
        }
      ],
      "title": "Top 10 Endpoints by Request Count",
      "type": "barchart"
    },
    {
      "datasource": { "type": "prometheus", "uid": "${DS_PROMETHEUS}" },
      "description": "Top 10 slowest endpoints ranked by P95 latency over the selected time range",
      "fieldConfig": {
        "defaults": {
          "color": { "mode": "palette-classic" },
          "custom": {
            "axisBorderShow": false,
            "axisCenteredZero": false,
            "axisLabel": "latency",
            "axisPlacement": "auto",
            "fillOpacity": 80,
            "gradientMode": "none",
            "hideFrom": { "legend": false, "tooltip": false, "viz": false },
            "lineWidth": 1,
            "scaleDistribution": { "type": "linear" }
          },
          "mappings": [],
          "thresholds": {
            "mode": "absolute",
            "steps": [
              { "color": "green", "value": null },
              { "color": "orange", "value": 1 },
              { "color": "red", "value": 2 }
            ]
          },
          "unit": "s"
        },
        "overrides": []
      },
      "gridPos": { "h": 8, "w": 12, "x": 12, "y": 10 },
      "id": 6,
      "options": {
        "barRadius": 0.1,
        "barWidth": 0.7,
        "fullHighlight": false,
        "groupWidth": 0.7,
        "legend": { "displayMode": "list", "placement": "bottom" },
        "orientation": "horizontal",
        "showValue": "auto",
        "stacking": "none",
        "tooltip": { "mode": "single", "sort": "none" },
        "xTickLabelRotation": 0
      },
      "targets": [
        {
          "datasource": { "type": "prometheus", "uid": "${DS_PROMETHEUS}" },
          "editorMode": "code",
          "expr": "topk(10, histogram_quantile(0.95, sum by (le, path_template) (rate(http_request_duration_seconds_bucket[5m]))))",
          "legendFormat": "{{path_template}}",
          "instant": true,
          "refId": "A"
        }
      ],
      "title": "Top 10 Slowest Endpoints (P95 Latency)",
      "type": "barchart"
    },
    {
      "collapsed": false,
      "gridPos": { "h": 1, "w": 24, "x": 0, "y": 18 },
      "id": 300,
      "title": "Agent Health",
      "type": "row"
    },
    {
      "datasource": { "type": "prometheus", "uid": "${DS_PROMETHEUS}" },
      "description": "Investigation agent status. Uses agent heartbeat metric when available.",
      "fieldConfig": {
        "defaults": {
          "color": { "mode": "thresholds" },
          "mappings": [
            { "options": { "0": { "color": "red", "text": "OFFLINE" } }, "type": "value" },
            { "options": { "1": { "color": "green", "text": "HEALTHY" } }, "type": "value" },
            {
              "options": { "from": -1, "result": { "color": "dark-grey", "text": "NO DATA" }, "to": -1 },
              "type": "range"
            }
          ],
          "noValue": "NO DATA",
          "thresholds": {
            "mode": "absolute",
            "steps": [
              { "color": "dark-grey", "value": null },
              { "color": "red", "value": 0 },
              { "color": "green", "value": 1 }
            ]
          }
        },
        "overrides": []
      },
      "gridPos": { "h": 4, "w": 4, "x": 0, "y": 19 },
      "id": 10,
      "options": {
        "colorMode": "background",
        "graphMode": "none",
        "justifyMode": "center",
        "orientation": "auto",
        "reduceOptions": {
          "calcs": ["lastNotNull"],
          "fields": "",
          "values": false
        },
        "textMode": "value",
        "wideLayout": true
      },
      "targets": [
        {
          "datasource": { "type": "prometheus", "uid": "${DS_PROMETHEUS}" },
          "editorMode": "code",
          "expr": "shieldops_agent_healthy{agent_type=\"investigation\"} or vector(-1)",
          "legendFormat": "",
          "instant": true,
          "refId": "A"
        }
      ],
      "title": "Investigation Agent",
      "type": "stat"
    },
    {
      "datasource": { "type": "prometheus", "uid": "${DS_PROMETHEUS}" },
      "description": "Remediation agent status. Uses agent heartbeat metric when available.",
      "fieldConfig": {
        "defaults": {
          "color": { "mode": "thresholds" },
          "mappings": [
            { "options": { "0": { "color": "red", "text": "OFFLINE" } }, "type": "value" },
            { "options": { "1": { "color": "green", "text": "HEALTHY" } }, "type": "value" },
            {
              "options": { "from": -1, "result": { "color": "dark-grey", "text": "NO DATA" }, "to": -1 },
              "type": "range"
            }
          ],
          "noValue": "NO DATA",
          "thresholds": {
            "mode": "absolute",
            "steps": [
              { "color": "dark-grey", "value": null },
              { "color": "red", "value": 0 },
              { "color": "green", "value": 1 }
            ]
          }
        },
        "overrides": []
      },
      "gridPos": { "h": 4, "w": 4, "x": 4, "y": 19 },
      "id": 11,
      "options": {
        "colorMode": "background",
        "graphMode": "none",
        "justifyMode": "center",
        "orientation": "auto",
        "reduceOptions": {
          "calcs": ["lastNotNull"],
          "fields": "",
          "values": false
        },
        "textMode": "value",
        "wideLayout": true
      },
      "targets": [
        {
          "datasource": { "type": "prometheus", "uid": "${DS_PROMETHEUS}" },
          "editorMode": "code",
          "expr": "shieldops_agent_healthy{agent_type=\"remediation\"} or vector(-1)",
          "legendFormat": "",
          "instant": true,
          "refId": "A"
        }
      ],
      "title": "Remediation Agent",
      "type": "stat"
    },
    {
      "datasource": { "type": "prometheus", "uid": "${DS_PROMETHEUS}" },
      "description": "Security agent status. Uses agent heartbeat metric when available.",
      "fieldConfig": {
        "defaults": {
          "color": { "mode": "thresholds" },
          "mappings": [
            { "options": { "0": { "color": "red", "text": "OFFLINE" } }, "type": "value" },
            { "options": { "1": { "color": "green", "text": "HEALTHY" } }, "type": "value" },
            {
              "options": { "from": -1, "result": { "color": "dark-grey", "text": "NO DATA" }, "to": -1 },
              "type": "range"
            }
          ],
          "noValue": "NO DATA",
          "thresholds": {
            "mode": "absolute",
            "steps": [
              { "color": "dark-grey", "value": null },
              { "color": "red", "value": 0 },
              { "color": "green", "value": 1 }
            ]
          }
        },
        "overrides": []
      },
      "gridPos": { "h": 4, "w": 4, "x": 8, "y": 19 },
      "id": 12,
      "options": {
        "colorMode": "background",
        "graphMode": "none",
        "justifyMode": "center",
        "orientation": "auto",
        "reduceOptions": {
          "calcs": ["lastNotNull"],
          "fields": "",
          "values": false
        },
        "textMode": "value",
        "wideLayout": true
      },
      "targets": [
        {
          "datasource": { "type": "prometheus", "uid": "${DS_PROMETHEUS}" },
          "editorMode": "code",
          "expr": "shieldops_agent_healthy{agent_type=\"security\"} or vector(-1)",
          "legendFormat": "",
          "instant": true,
          "refId": "A"
        }
      ],
      "title": "Security Agent",
      "type": "stat"
    },
    {
      "datasource": { "type": "prometheus", "uid": "${DS_PROMETHEUS}" },
      "description": "Cost agent status. Uses agent heartbeat metric when available.",
      "fieldConfig": {
        "defaults": {
          "color": { "mode": "thresholds" },
          "mappings": [
            { "options": { "0": { "color": "red", "text": "OFFLINE" } }, "type": "value" },
            { "options": { "1": { "color": "green", "text": "HEALTHY" } }, "type": "value" },
            {
              "options": { "from": -1, "result": { "color": "dark-grey", "text": "NO DATA" }, "to": -1 },
              "type": "range"
            }
          ],
          "noValue": "NO DATA",
          "thresholds": {
            "mode": "absolute",
            "steps": [
              { "color": "dark-grey", "value": null },
              { "color": "red", "value": 0 },
              { "color": "green", "value": 1 }
            ]
          }
        },
        "overrides": []
      },
      "gridPos": { "h": 4, "w": 4, "x": 12, "y": 19 },
      "id": 13,
      "options": {
        "colorMode": "background",
        "graphMode": "none",
        "justifyMode": "center",
        "orientation": "auto",
        "reduceOptions": {
          "calcs": ["lastNotNull"],
          "fields": "",
          "values": false
        },
        "textMode": "value",
        "wideLayout": true
      },
      "targets": [
        {
          "datasource": { "type": "prometheus", "uid": "${DS_PROMETHEUS}" },
          "editorMode": "code",
          "expr": "shieldops_agent_healthy{agent_type=\"cost\"} or vector(-1)",
          "legendFormat": "",
          "instant": true,
          "refId": "A"
        }
      ],
      "title": "Cost Agent",
      "type": "stat"
    },
    {
      "datasource": { "type": "prometheus", "uid": "${DS_PROMETHEUS}" },
      "description": "Learning agent status. Uses agent heartbeat metric when available.",
      "fieldConfig": {
        "defaults": {
          "color": { "mode": "thresholds" },
          "mappings": [
            { "options": { "0": { "color": "red", "text": "OFFLINE" } }, "type": "value" },
            { "options": { "1": { "color": "green", "text": "HEALTHY" } }, "type": "value" },
            {
              "options": { "from": -1, "result": { "color": "dark-grey", "text": "NO DATA" }, "to": -1 },
              "type": "range"
            }
          ],
          "noValue": "NO DATA",
          "thresholds": {
            "mode": "absolute",
            "steps": [
              { "color": "dark-grey", "value": null },
              { "color": "red", "value": 0 },
              { "color": "green", "value": 1 }
            ]
          }
        },
        "overrides": []
      },
      "gridPos": { "h": 4, "w": 4, "x": 16, "y": 19 },
      "id": 14,
      "options": {
        "colorMode": "background",
        "graphMode": "none",
        "justifyMode": "center",
        "orientation": "auto",
        "reduceOptions": {
          "calcs": ["lastNotNull"],
          "fields": "",
          "values": false
        },
        "textMode": "value",
        "wideLayout": true
      },
      "targets": [
        {
          "datasource": { "type": "prometheus", "uid": "${DS_PROMETHEUS}" },
          "editorMode": "code",
          "expr": "shieldops_agent_healthy{agent_type=\"learning\"} or vector(-1)",
          "legendFormat": "",
          "instant": true,
          "refId": "A"
        }
      ],
      "title": "Learning Agent",
      "type": "stat"
    },
    {
      "datasource": { "type": "prometheus", "uid": "${DS_PROMETHEUS}" },
      "description": "Supervisor agent status. Uses agent heartbeat metric when available.",
      "fieldConfig": {
        "defaults": {
          "color": { "mode": "thresholds" },
          "mappings": [
            { "options": { "0": { "color": "red", "text": "OFFLINE" } }, "type": "value" },
            { "options": { "1": { "color": "green", "text": "HEALTHY" } }, "type": "value" },
            {
              "options": { "from": -1, "result": { "color": "dark-grey", "text": "NO DATA" }, "to": -1 },
              "type": "range"
            }
          ],
          "noValue": "NO DATA",
          "thresholds": {
            "mode": "absolute",
            "steps": [
              { "color": "dark-grey", "value": null },
              { "color": "red", "value": 0 },
              { "color": "green", "value": 1 }
            ]
          }
        },
        "overrides": []
      },
      "gridPos": { "h": 4, "w": 4, "x": 20, "y": 19 },
      "id": 15,
      "options": {
        "colorMode": "background",
        "graphMode": "none",
        "justifyMode": "center",
        "orientation": "auto",
        "reduceOptions": {
          "calcs": ["lastNotNull"],
          "fields": "",
          "values": false
        },
        "textMode": "value",
        "wideLayout": true
      },
      "targets": [
        {
          "datasource": { "type": "prometheus", "uid": "${DS_PROMETHEUS}" },
          "editorMode": "code",
          "expr": "shieldops_agent_healthy{agent_type=\"supervisor\"} or vector(-1)",
          "legendFormat": "",
          "instant": true,
          "refId": "A"
        }
      ],
      "title": "Supervisor Agent",
      "type": "stat"
    }
  ],
  "refresh": "30s",
  "schemaVersion": 39,
  "tags": ["shieldops", "sre", "overview"],
  "templating": {
    "list": [
      {
        "current": {
          "selected": false,
          "text": "Prometheus",
          "value": "Prometheus"
        },
        "hide": 0,
        "includeAll": false,
        "multi": false,
        "name": "DS_PROMETHEUS",
        "options": [],
        "query": "prometheus",
        "queryValue": "",
        "refresh": 1,
        "regex": "",
        "skipUrlSync": false,
        "type": "datasource"
      }
    ]
  },
  "time": {
    "from": "now-1h",
    "to": "now"
  },
  "timepicker": {
    "refresh_intervals": ["5s", "10s", "30s", "1m", "5m"],
    "time_options": ["5m", "15m", "1h", "6h", "12h", "24h", "2d", "7d"]
  },
  "timezone": "browser",
  "title": "ShieldOps Overview",
  "uid": "shieldops-overview",
  "version": 1,
  "weekStart": ""
}
